carto_bq_tiler/__init__.py
carto_bq_tiler/assets/bigquery_viewer.html
carto_bq_tiler/assets/bigquery_viewer_compare.html
carto_bq_tiler/assets/file_viewer.html
carto_bq_tiler/bigquery.py
carto_bq_tiler/carto_bq_tiler.py
carto_bq_tiler/exceptions.py
carto_bq_tiler/export.py
carto_bq_tiler/http_server.py
carto_bq_tiler/lib/__init__.py
carto_bq_tiler/lib/vector_tile_base/__init__.py
carto_bq_tiler/lib/vector_tile_base/engine.py
carto_bq_tiler/lib/vector_tile_base/vector_tile_pb2.py
carto_bq_tiler/mbtiles.py
carto_bq_tiler/settings.py
carto_bq_tiler/tile_utils.py
carto_bq_tiler/utils.py
carto_bq_tiler-0.1.10.dist-info/entry_points.txt
carto_bq_tiler-0.1.10.dist-info/WHEEL
carto_bq_tiler-0.1.10.dist-info/METADATA
carto_bq_tiler-0.1.10.dist-info/RECORD
