Metadata-Version: 2.1
Name: carto-bq-tiler
Version: 0.1.10
Summary: CARTO BigQuery Tiler cli
Author: CARTO
Author-email: support@carto.com
Requires-Python: >=3.5.3,<4.0.0
Classifier: Programming Language :: Python :: 3
Classifier: Programming Language :: Python :: 3.6
Classifier: Programming Language :: Python :: 3.7
Classifier: Programming Language :: Python :: 3.8
Requires-Dist: Shapely (==1.7.0)
Requires-Dist: click (==7.1.2)
Requires-Dist: click-spinner (==0.1.10)
Requires-Dist: google-api-core (==1.17.0)
Requires-Dist: google-auth (==1.14.2)
Requires-Dist: google-cloud-bigquery (==1.24.0)
Requires-Dist: google-cloud-bigquery-storage[fastavro] (==0.8.0)
Requires-Dist: google-cloud-core (==1.3.0)
Requires-Dist: grpcio (==1.28.1)
Requires-Dist: mercantile (==1.1.4)
Requires-Dist: pyproj (==2.5.0)
